setup.cfg
setup.py
cosmos/__init__.py
cosmos/cli.py
cosmos/constants.py
cosmos/data.py
cosmos/types.py
cosmos/utils.py
cosmos_osm.egg-info/PKG-INFO
cosmos_osm.egg-info/SOURCES.txt
cosmos_osm.egg-info/dependency_links.txt
cosmos_osm.egg-info/entry_points.txt
cosmos_osm.egg-info/requires.txt
cosmos_osm.egg-info/top_level.txt