Metadata-Version: 1.0
Name: cosmos-osm
Version: 0.0.1
Summary: Package for easy OSM data download
Home-page: https://github.com/astrosat/cOSMos
Author: Waldemar Franczak
Author-email: waldemar.franczak@astrosat.biz
License: MIT
Platform: UNKNOWN
